{"PERSON||William Chen": "William Chen", "DATE_TIME||1988-05-21": "1994-06-22", "PHONE_NUMBER||(312) 555-0199": "(687) 204-1082", "EMAIL_ADDRESS||william.chen@example.com": "william.chen@yahoo.com", "PERSON||Email": "Email", "LOCATION||Chicago": "Chicago", "ORGANIZATION||Social Security Number": "Social Security Number", "DATE_TIME||2006-2010": "0207-0821", "ORGANIZATION||Computer Science": "Computer Science", "ORGANIZATION||University of Illinois - B.S.": "University of Illinois - B.S.", "DATE_TIME||2010-2015": "6637-0800", "ORGANIZATION||ABC Technologies - Software Engineer": "ABC Technologies - Software Engineer", "DATE_TIME||2015-2020": "5643-6335", "ORGANIZATION||XYZ Security Consulting - Cybersecurity Consultant": "XYZ Security Consulting - Cybersecurity Consultant"}